ibm_ray_config/__init__.py
ibm_ray_config/main.py
ibm_ray_config/modules/__init__.py
ibm_ray_config/modules/api_key.py
ibm_ray_config/modules/cleanup.py
ibm_ray_config/modules/config_builder.py
ibm_ray_config/modules/utils.py
ibm_ray_config/modules/gen2/__init__.py
ibm_ray_config/modules/gen2/endpoint.py
ibm_ray_config/modules/gen2/image.py
ibm_ray_config/modules/gen2/ssh_key.py
ibm_ray_config/modules/gen2/verify.py
ibm_ray_config/modules/gen2/ray/__init__.py
ibm_ray_config/modules/gen2/ray/api_key.py
ibm_ray_config/modules/gen2/ray/defaults.yaml
ibm_ray_config/modules/gen2/ray/defaults_pr.yaml
ibm_ray_config/modules/gen2/ray/endpoint.py
ibm_ray_config/modules/gen2/ray/floating_ip.py
ibm_ray_config/modules/gen2/ray/image.py
ibm_ray_config/modules/gen2/ray/ssh_key.py
ibm_ray_config/modules/gen2/ray/vpc.py
ibm_ray_config/modules/gen2/ray/workers.py
ibm_ray_config-1.0.0b30.data/scripts/ibm-ray-config
ibm_ray_config-1.0.0b30.dist-info/LICENSE
ibm_ray_config-1.0.0b30.dist-info/METADATA
ibm_ray_config-1.0.0b30.dist-info/WHEEL
ibm_ray_config-1.0.0b30.dist-info/top_level.txt
ibm_ray_config-1.0.0b30.dist-info/RECORD
