Metadata-Version: 2.1
Name: ibm-ray-config
Version: 1.0.0b30
Summary: Interactive tool generating ray configuration for IBM platforms
Home-page: https://github.com/project-codeflare/ibm-ray-config
Author: Omer J Cohen
Author-email: cohen.j.omer@gmail.com
Classifier: Programming Language :: Python :: 3
Requires-Python: >=3.6
License-File: LICENSE
Requires-Dist: click >=8.0.1
Requires-Dist: inquirer >=2.7.0
Requires-Dist: ibm-cloud-sdk-core
Requires-Dist: ibm-platform-services
Requires-Dist: PyYAML >=5.4.1
Requires-Dist: ibm-watson
Requires-Dist: docker >=5.0.3
Requires-Dist: ibm-vpc
Requires-Dist: ibm-vpc-ray-connector
